{
  "texture": {
    "in": "skyhighocs:chase/pryetak_nebula_predation_sides_wave_changing_lights",
    "transform": [
      {
        "operation": "XOR",
        "supply": "skyhighheroes:xor/predation_sides_wave_changing_lights_<TIMER>"
      }
    ],
    "out": "skyhighocs:generated/pryetak_nebula_predation_bottom_wave_changing_lights_<TIMER>"
  },
  "getters": {
    "TIMER": {
      "key": "Math.min(Math.max(Math.ceil(28 - ((entity.getData('skyhighheroes:dyn/sword') ? -1 : 1) * 28 * entity.getInterpolatedData('skyhighheroes:dyn/sword_timer') + (entity.getData('skyhighheroes:dyn/sword') ? 28 : 0)) - ((entity.getData('skyhighocs:dyn/galaxys_weight') ? -1 : 1) * 28 * entity.getInterpolatedData('skyhighocs:dyn/galaxys_weight_timer') + (entity.getData('skyhighocs:dyn/galaxys_weight') ? 28 : 0)) - ((entity.getData('skyhighocs:dyn/voids_grasp') ? -1 : 1) * 28 * entity.getInterpolatedData('skyhighocs:dyn/voids_grasp_timer') + (entity.getData('skyhighocs:dyn/voids_grasp') ? 28 : 0)) - ((entity.getData('skyhighocs:dyn/nebula_burst') ? -1 : 1) * 28 * entity.getInterpolatedData('skyhighocs:dyn/nebula_burst_timer') + (entity.getData('skyhighocs:dyn/nebula_burst') ? 28 : 0)) - ((!entity.getHeldItem().isEmpty() ? -1 : 1) * 28 * entity.getInterpolatedData('skyhighheroes:dyn/item_holding_timer') + (!entity.getHeldItem().isEmpty() ? 28 : 0))), 2), 28) | 0",
      "values": {
        "min": 2,
        "max": 28
      }
    }
  },
  "isDynamic": true
}